{
  "id": "lt-law-xiv-487",
  "type": "statute",
  "title": "Lietuvos Respublikos vietos savivaldos įstatymo Nr. I-533 7 straipsnio pakeitimo įstatymas",
  "short_name": "XIV-487",
  "status": "in_force",
  "issued_date": "2021-06-30",
  "in_force_date": "2021-09-01",
  "url": "https://e-tar.lt/portal/lt/legalAct/193edb10e46d11eb9f09e7df20500045/NlqykdStEp",
  "provisions": [
    {
      "provision_ref": "art1",
      "section": "1",
      "title": "1 straipsnis. 7 straipsnio pakeitimas",
      "content": "Pakeisti 7 straipsnio 39 punktą ir jį išdėstyti taip:\n\n„39) koordinuotai teikiamų paslaugų vaikams nuo gimimo iki 18 metų (turintiems didelių ir labai didelių specialiųjų ugdymosi poreikių – iki mokslo metų, kuriais jiems sueina 21 metai, pabaigos, o tiems, kurie dėl ligos mokėsi su pertraukomis ir pateikė tokių pertraukų priežastį pagrindžiančius dokumentus, – iki mokslo metų, kuriais jiems sueina 23 metai, pabaigos) ir vaiko atstovams pagal įstatymą koordinavimas;“."
    },
    {
      "provision_ref": "art2",
      "section": "2",
      "title": "2 straipsnis. Įstatymo įsigaliojimas ir įgyvendinimas",
      "content": "1. Šis įstatymas, išskyrus šio straipsnio 2 dalį, įsigalioja 2021 m. rugsėjo 1 d.\n\n2. Lietuvos Respublikos švietimo, mokslo ir sporto ministras, Lietuvos Respublikos socialinės apsaugos ir darbo ministras ir Lietuvos Respublikos sveikatos apsaugos ministras iki 2021 m. rugpjūčio 31 d. priima šio įstatymo įgyvendinamuosius teisės aktus.\n\nSkelbiu šį Lietuvos Respublikos Seimo priimtą įstatymą.\n\nRespublikos Prezidentas                                                                                            Gitanas Nausėda"
    }
  ],
  "definitions": []
}
