{
  "id": "lt-law-xii-1042",
  "type": "statute",
  "title": "Lietuvos Respublikos kredito unijų įstatymo Nr. I-796 4 ir 9 straipsnių pakeitimo įstatymas",
  "short_name": "XII-1042",
  "status": "in_force",
  "issued_date": "2014-07-17",
  "in_force_date": "2014-11-01",
  "url": "https://e-tar.lt/portal/lt/legalAct/9d76aa601b9e11e4b542dec0b12e28b0/WUbNULUdnn",
  "provisions": [
    {
      "provision_ref": "art1",
      "section": "1",
      "title": "1 straipsnis. 4 straipsnio pakeitimas",
      "content": "1. Pakeisti 4 straipsnio 1 dalį ir ją išdėstyti taip:\n\n„1. Kredito unija privalo teikti šio straipsnio 2 dalies 1 punkte nustatytą licencinę finansinę paslaugą ir turi teisę teikti šio straipsnio 2 dalies 2 ir 4 punktuose ir 3 dalyje nustatytas finansines paslaugas, įskaitant finansines paslaugas užsienio valiuta, jeigu šios teisės neapribotos šio ar kitų įstatymų nustatyta tvarka.“\n\n2. Pripažinti netekusiu galios 4 straipsnio 2 dalies 3 punktą.\n\n3. Papildyti 4 straipsnio 3 dalį 9 punktu:\n\n„9) valiutos keitimas (grynaisiais pinigais).“"
    },
    {
      "provision_ref": "art2",
      "section": "2",
      "title": "2 straipsnis. 9 straipsnio pakeitimas",
      "content": "Pripažinti netekusia galios 9 straipsnio 1 dalį."
    },
    {
      "provision_ref": "art3",
      "section": "3",
      "title": "3 straipsnis. Įstatymo įsigaliojimas",
      "content": "Šis įstatymas įsigalioja 2014 m. lapkričio 1 d.\n\nSkelbiu šį Lietuvos Respublikos Seimo priimtą įstatymą.\n\nRespublikos Prezidentė                                                                             Dalia Grybauskaitė"
    }
  ],
  "definitions": []
}
