{
  "id": "lt-law-xii-1620",
  "type": "statute",
  "title": "Lietuvos Respublikos valstybės ir savivaldybės įmonių įstatymo Nr. I-722 15 straipsnio pakeitimo įstatymas",
  "short_name": "XII-1620",
  "status": "in_force",
  "issued_date": "2015-04-16",
  "in_force_date": "2015-05-01",
  "url": "https://e-tar.lt/portal/lt/legalAct/a59abb40ef2f11e4927fda1d051299fb/TBixAMxcUf",
  "provisions": [
    {
      "provision_ref": "art1",
      "section": "1",
      "title": "1 straipsnis. 15 straipsnio pakeitimas",
      "content": "1. Papildyti 15 straipsnį nauja 9 dalimi:\n\n„9. Valstybės įmonės pelno dalis, atitinkanti valstybės įmonės pelno įmokos, nuo kurios mokėjimo į valstybės biudžetą ji atleidžiama vadovaujantis šio straipsnio 7 dalimi, dydį, taip pat valstybės įmonės pelno dalis, atitinkanti valstybės įmonės pelno įmokos, kurios mokėjimo į valstybės biudžetą dydis yra mažinamas vadovaujantis šio straipsnio 6 dalies 1 punktu, sumažintą dalį, turi būti skiriamos teisės aktais pripažintiems ypatingos valstybinės svarbos arba valstybei svarbiems ekonominiams projektams, kuriuos ši valstybės įmonė įgyvendina arba dalyvauja juos įgyvendinant.“\n\n2. Buvusią 15 straipsnio 9 dalį laikyti 10 dalimi."
    },
    {
      "provision_ref": "art2",
      "section": "2",
      "title": "2 straipsnis. Įstatymo taikymas",
      "content": "Šis įstatymas taikomas dėl valstybės įmonės 2015 ir vėlesnių finansinių metų pelno dalies skyrimo teisės aktais pripažintiems ypatingos valstybinės svarbos arba valstybei svarbiems ekonominiams projektams, kuriuos ši valstybės įmonė įgyvendina arba dalyvauja juos įgyvendinant, įgyvendinti.\n\nSkelbiu šį Lietuvos Respublikos Seimo priimtą įstatymą.\n\nRespublikos Prezidentė                                                                                          Dalia Grybauskaitė"
    }
  ],
  "definitions": []
}
