{
  "id": "lt-law-xiii-2946",
  "type": "statute",
  "title": "Lietuvos Respublikos vietos savivaldos įstatymo Nr. I-533 6 straipsnio pakeitimo įstatymas",
  "short_name": "XIII-2946",
  "status": "in_force",
  "issued_date": "2020-05-21",
  "in_force_date": "2020-07-01",
  "url": "https://e-tar.lt/portal/lt/legalAct/a9d9f640a19e11ea9515f752ff221ec9/BljfsIudRK",
  "provisions": [
    {
      "provision_ref": "art1",
      "section": "1",
      "title": "1 straipsnis. 6 straipsnio pakeitimas",
      "content": "Pakeisti 6 straipsnio 12 punktą ir jį išdėstyti taip:\n\n„12) socialinių paslaugų teikimo užtikrinimas planuojant ir organizuojant socialines paslaugas, kontroliuojant bendrųjų socialinių paslaugų ir socialinės priežiūros kokybę, taip pat socialinių paslaugų įstaigų steigimas ir išlaikymas;“."
    },
    {
      "provision_ref": "art2",
      "section": "2",
      "title": "2 straipsnis. Įstatymo įsigaliojimas",
      "content": "Šis įstatymas įsigalioja 2020 m. liepos 1 d.\n\nSkelbiu šį Lietuvos Respublikos Seimo priimtą įstatymą.\n\nRespublikos Prezidentas                                                                                          Gitanas Nausėda"
    }
  ],
  "definitions": []
}
