{
  "id": "lt-law-xiv-2460",
  "type": "statute",
  "title": "Lietuvos Respublikos vietos savivaldos įstatymo Nr. I-533 8 ir 26 straipsnių pakeitimo įstatymas",
  "short_name": "XIV-2460",
  "status": "in_force",
  "issued_date": "2023-12-23",
  "in_force_date": "2023-12-30",
  "url": "https://e-tar.lt/portal/lt/legalAct/aec369e0a62f11eea5a28c81c82193a8/qnCJcJlLSa",
  "provisions": [
    {
      "provision_ref": "art1",
      "section": "1",
      "title": "1 straipsnis. 8 straipsnio pakeitimas",
      "content": "Pakeisti 8 straipsnio 4 dalį ir ją išdėstyti taip:\n\n„4. Nustatomas toks išrinkto savivaldybės tarybos nario priesaikos tekstas:\n„Aš, (vardas, pavardė), prisiekiu gerbti ir vykdyti Lietuvos Respublikos Konstituciją ir įstatymus, sąžiningai ir garbingai atlikti savo pareigas ir susilaikyti nuo veiksmų, pažeidžiančių savivaldybės gyventojų teises ir viešuosius interesus. Tepadeda man Dievas!“.“"
    },
    {
      "provision_ref": "art2",
      "section": "2",
      "title": "2 straipsnis. 26 straipsnio pakeitimas",
      "content": "Pakeisti 26 straipsnio 1 dalį ir ją išdėstyti taip:\n\n„1. Nustatomas toks išrinkto mero priesaikos tekstas:\n„Aš, (vardas, pavardė), prisiekiu gerbti ir vykdyti Lietuvos Respublikos Konstituciją ir įstatymus, sąžiningai ir garbingai atlikti savo pareigas ir susilaikyti nuo veiksmų, pažeidžiančių savivaldybės gyventojų teises ir viešuosius interesus. Tepadeda man Dievas!“.“\n\nSkelbiu šį Lietuvos Respublikos Seimo priimtą įstatymą.\n\nRespublikos Prezidentas                                                                                          Gitanas Nausėda"
    }
  ],
  "definitions": []
}
