{
  "id": "lt-law-xii-1890",
  "type": "statute",
  "title": "Lietuvos Respublikos naftos produktų ir naftos valstybės atsargų įstatymo Nr. IX-986 4 straipsnio pakeitimo įstatymas",
  "short_name": "XII-1890",
  "status": "in_force",
  "issued_date": "2015-06-25",
  "in_force_date": "2016-01-01",
  "url": "https://e-tar.lt/portal/lt/legalAct/b6a86b1024a611e5b336e9064144f02a/ugfMbxkOMm",
  "provisions": [
    {
      "provision_ref": "art1",
      "section": "1",
      "title": "1 straipsnis. 4 straipsnio pakeitimas",
      "content": "Pakeisti 4 straipsnio 3 dalį ir ją išdėstyti taip:\n\n„3. Atsargų kokybę Taisyklėse nustatyta tvarka kontroliuoja Valstybinė vartotojų teisių apsaugos tarnyba.“"
    },
    {
      "provision_ref": "art2",
      "section": "2",
      "title": "2 straipsnis. Įstatymo įsigaliojimas ir įgyvendinimas",
      "content": "1. Šis įstatymas, išskyrus šio straipsnio 2 dalį, įsigalioja 2016 m. sausio 1 d.\n\n2. Lietuvos Respublikos Vyriausybė ir jos įgaliota institucija iki 2015 m. gruodžio 31 d. priima šio įstatymo įgyvendinamuosius teisės aktus.\n\nSkelbiu šį Lietuvos Respublikos Seimo priimtą įstatymą.\n\nRespublikos Prezidentė                                                                                        Dalia Grybauskaitė"
    }
  ],
  "definitions": []
}
