{
  "id": "lt-law-xiii-141",
  "type": "statute",
  "title": "Lietuvos Respublikos nedarbo socialinio draudimo įstatymo Nr. IX-1904 pakeitimo įstatymo Nr. XII-2471 2 straipsnio pakeitimo įstatymas",
  "short_name": "XIII-141",
  "status": "in_force",
  "issued_date": "2016-12-20",
  "in_force_date": "2016-12-29",
  "url": "https://e-tar.lt/portal/lt/legalAct/dceb0960ccfa11e6a2cac7383cbb90a3/FagLXYLXnU",
  "provisions": [
    {
      "provision_ref": "art1",
      "section": "1",
      "title": "1 straipsnis. 2 straipsnio pakeitimas",
      "content": "1. Pakeisti 2 straipsnio 1 dalį ir ją išdėstyti taip:\n\n„1. Šis įstatymas, išskyrus šio straipsnio 2 dalį, įsigalioja 2017 m. liepos 1 d.“\n\n2. Pakeisti 2 straipsnio 2 dalį ir ją išdėstyti taip:\n\n„2. Lietuvos Respublikos Vyriausybė ar jos įgaliota institucija iki 2017 m. birželio 30 d. priima šio įstatymo įgyvendinamuosius teisės aktus.“\n\nSkelbiu šį Lietuvos Respublikos Seimo priimtą įstatymą.\n\nRespublikos Prezidentė                                                                                        Dalia Grybauskaitė"
    }
  ],
  "definitions": []
}
