{
  "id": "lt-law-xiii-1004",
  "type": "statute",
  "title": "Lietuvos Respublikos nacionalinio saugumo pagrindų įstatymo Nr. VIII-49 priedėlio pakeitimo įstatymas",
  "short_name": "XIII-1004",
  "status": "in_force",
  "issued_date": "2018-01-12",
  "in_force_date": "2018-03-01",
  "url": "https://e-tar.lt/portal/lt/legalAct/e7f74c00004411e88bcec397524184ce/fcCtQxSnvu",
  "provisions": [
    {
      "provision_ref": "art1",
      "section": "1",
      "title": "1 straipsnis. Įstatymo priedėlio pakeitimas",
      "content": "Pakeisti Įstatymo priedėlio I dalies 4 skyriaus skirsnio „Ekonominė politika“ trečiąją pastraipą ir ją išdėstyti taip:\n\n„Strategiškai svarbūs nacionaliniam saugumui ūkio sektoriai Lietuvoje yra:\n– energetikos;\n– transporto;\n– informacinių technologijų ir telekomunikacijų, kitų aukštųjų technologijų;\n– finansų ir kredito;\n– karinės įrangos.“"
    },
    {
      "provision_ref": "art2",
      "section": "2",
      "title": "2 straipsnis. Įstatymo įsigaliojimas",
      "content": "Šis įstatymas įsigalioja 2018 m. kovo 1 d.\n\nSkelbiu šį Lietuvos Respublikos Seimo priimtą įstatymą.\n\nRespublikos Prezidentė                                                                                          Dalia Grybauskaitė"
    }
  ],
  "definitions": []
}
