{
  "id": "lt-law-xiv-62",
  "type": "statute",
  "title": "Lietuvos Respublikos gyventojų pajamų mokesčio įstatymo Nr. IX-1007 21 straipsnio pakeitimo įstatymas",
  "short_name": "XIV-62",
  "status": "in_force",
  "issued_date": "2020-12-10",
  "in_force_date": "2020-12-18",
  "url": "https://e-tar.lt/portal/lt/legalAct/f98535e0406a11eb8d9fe110e148c770/IunYscYCCV",
  "provisions": [
    {
      "provision_ref": "art1",
      "section": "1",
      "title": "1 straipsnis. 21 straipsnio pakeitimas",
      "content": "Pakeisti 21 straipsnio 1 dalies 3 punktą ir jį išdėstyti taip:\n\n„3) už profesinį mokymą pagal formaliojo profesinio mokymo programą, kurią baigus įgyjama atitinkama kvalifikacija, formaliojo profesinio mokymo programos modulį, kurį baigus įgyjama atitinkama kompetencija (kompetencijos), ir (ar) už studijas, kurias baigus įgyjama aukštojo mokslo kvalifikacija, nuolatinių Lietuvos gyventojų, kurie mokosi ar studijuoja, sumokėtos sumos. Jei už profesinį mokymą pagal formaliojo profesinio mokymo programą, formaliojo profesinio mokymo programos modulį ir (ar) už studijas sumokėta skolintomis lėšomis (tam tikslui paimta iš kredito įstaigos paskola), tai iš pajamų gali būti atimta per mokestinį laikotarpį grąžinta šios paskolos dalis;“."
    },
    {
      "provision_ref": "art2",
      "section": "2",
      "title": "2 straipsnis. Įstatymo įgyvendinimas ir taikymas",
      "content": "1. Valstybinė mokesčių inspekcija prie Lietuvos Respublikos finansų ministerijos iki 2020 m. gruodžio 31 d. priima šio įstatymo įgyvendinamuosius teisės aktus.\n\n2. Šio įstatymo nuostatos taikomos apskaičiuojant ir deklaruojant 2020 metų ir vėlesnių mokestinių laikotarpių pajamas.\n\nSkelbiu šį Lietuvos Respublikos Seimo priimtą įstatymą.\n\nRespublikos Prezidentas                                                                                          Gitanas Nausėda"
    }
  ],
  "definitions": []
}
