{
  "id": "lt-law-xi-2003",
  "type": "statute",
  "title": "Lietuvos Respublikos baudžiamojo proceso kodekso 114 straipsnio pakeitimo įstatymas",
  "short_name": "XI-2003",
  "status": "in_force",
  "issued_date": "2012-05-10",
  "in_force_date": "2013-03-01",
  "url": "https://e-tar.lt/portal/lt/legalAct/TAR.070DA87F0A77",
  "provisions": [
    {
      "provision_ref": "art1",
      "section": "1",
      "title": "1 straipsnis. 114 straipsnio pakeitimas",
      "content": "Pakeisti 114 straipsnį ir jį išdėstyti taip:\n\n„114 straipsnis. Civilinio ieškinio perdavimas bankroto bylą nagrinėjančiam teismui\n\nJeigu į baudžiamąją bylą kaip civilinis atsakovas įtraukta įmonė ar fizinis asmuo, kuriems iškelta bankroto byla, civilinis ieškinys šioje baudžiamojoje byloje gali būti nenagrinėjamas, o visi su civiliniu ieškiniu susiję dokumentai prokuroro nutarimu ar teismo nutartimi gali būti perduodami bankroto bylą nagrinėjančiam teismui. Apie tai turi būti pranešta civiliniam ieškovui ir jam turi būti išaiškintos jo teisės bankroto byloje.“"
    },
    {
      "provision_ref": "art2",
      "section": "2",
      "title": "2 straipsnis. Įstatymo įsigaliojimas",
      "content": "Šis įstatymas įsigalioja 2013 m. kovo 1 d.\n\nSkelbiu šį Lietuvos Respublikos Seimo priimtą įstatymą.\n\nRESPUBLIKOS PREZIDENTĖ                                                    DALIA GRYBAUSKAITĖ\n\n_________________"
    }
  ],
  "definitions": []
}
