{
  "id": "lt-law-viii-299",
  "type": "statute",
  "title": "Lietuvos Respublikos vietos savivaldos įstatymo 16 straipsnio pakeitimo įstatymas",
  "short_name": "VIII-299",
  "status": "in_force",
  "issued_date": "1997-06-24",
  "in_force_date": "1997-07-01",
  "url": "https://e-tar.lt/portal/lt/legalAct/TAR.0B55CE42BA59",
  "provisions": [
    {
      "provision_ref": "art1",
      "section": "1",
      "title": "1 straipsnis. 16 straipsnis pakeitimas",
      "content": "Pakeisti 16 straipsnį ir jį išdėstyti taip:\n\n„16 straipsnis. Valstybės deleguotoji kompetencija\n\nSavivaldos institucijos atlieka civilinės metrikacijos funkcijas, tvarko savivaldybių ir valstybinių bei privataus kapitalo įmonių, visuomeninių organizacijų registrą, įgyvendina antrinę sveikatos priežiūrą, taip pat gali valdyti valstybinius parkus (nacionalinius ir regioninius), organizuoti savivaldybių policiją, civilinę ir priešgaisrinę saugą, įgyvendinti kitas įstatymų deleguotas funkcijas.\n\nSavivaldos institucijos, įgyvendindamos deleguotas valstybės funkcijas, vadovaujasi įstatymais, vykdo Vyriausybės nutarimus.“\n\nSkelbiu šį Lietuvos Respublikos Seimo priimtą įstatymą.\n\nRESPUBLIKOS PREZIDENTAS                                                       ALGIRDAS BRAZAUSKAS\n______________"
    }
  ],
  "definitions": []
}
