{
  "id": "lt-law-ix-2380",
  "type": "statute",
  "title": "Lietuvos Respublikos aplinkos apsaugos rėmimo programos įstatymo 3 straipsnio pakeitimo įstatymas",
  "short_name": "IX-2380",
  "status": "in_force",
  "issued_date": "2004-07-15",
  "in_force_date": "2004-07-27",
  "url": "https://e-tar.lt/portal/lt/legalAct/TAR.286D42A988FC/PGCRlXhhNe",
  "provisions": [
    {
      "provision_ref": "art1",
      "section": "1",
      "title": "1 straipsnis. 3 straipsnio 3 punkto pakeitimas",
      "content": "Pakeisti 3 straipsnio 3 punktą ir jį išdėstyti taip:\n\n„3) lėšos, gautos kaip didesnio tarifo mokestis už aplinkos teršimą, kai šis mokestis taikomas už nuslėptą teršalų ir apmokestinamųjų gaminių bei apmokestinamosios pakuotės kiekį, už normatyvus viršijantį teršalų kiekį, taip pat lėšos iš baudų už nuslėptą, limitus viršijantį, sugadintą valstybinių gamtos išteklių kiekį ar valstybinių gamtos išteklių, kurių panaudojimo sąlygos buvo pablogintos, kiekį;“.\n\nSkelbiu šį Lietuvos Respublikos Seimo priimtą įstatymą.\n\nRESPUBLIKOS PREZIDENTAS                                                                  VALDAS ADAMKUS"
    }
  ],
  "definitions": []
}
