{
  "id": "lt-law-xi-999",
  "type": "statute",
  "title": "Lietuvos Respublikos civilinio proceso kodekso 585 straipsnio pakeitimo ir papildymo įstatymas",
  "short_name": "XI-999",
  "status": "in_force",
  "issued_date": "2010-07-02",
  "in_force_date": "2010-07-15",
  "url": "https://e-tar.lt/portal/lt/legalAct/TAR.52BC54F4173E",
  "provisions": [
    {
      "provision_ref": "art1",
      "section": "1",
      "title": "1 straipsnis. 585 straipsnio pakeitimas ir papildymas",
      "content": "1. Pakeisti 585 straipsnio 2 dalį ir ją išdėstyti taip:\n\n„2. Asmeniui, kuris nevykdo antstolio reikalavimo ar kitaip kliudo antstoliui vykdyti vykdomuosius dokumentus, teismas gali skirti iki vieno tūkstančio litų (o kai antstolis vykdo teismo sprendimo nugriauti statinį (jo dalį) vykdomuosius dokumentus, – iki dviejų šimtų litų už kiekvieną nevykdymo dieną) dydžio baudą. Jeigu antstoliui kas nors kliudo vykdyti vykdomuosius dokumentus, antstolis kliūtims pašalinti kviečia policiją. Šiuo atveju policijos dalyvavimas būtinas.“\n\n2. Papildyti 585 straipsnį nauja 3 dalimi:\n\n„3. Jeigu antstolio reikalavimo nevykdo ar kitaip antstoliui vykdyti vykdomuosius dokumentus kliudo juridinis asmuo, šio straipsnio 2 dalyje numatytą baudą teismas gali skirti juridinio asmens vadovui arba kitam už sprendimo įvykdymą atsakingam asmeniui.“\n\n3. Buvusią 585 straipsnio 3 dalį laikyti 4 dalimi.\n\nSkelbiu šį Lietuvos Respublikos Seimo priimtą įstatymą.\n\nRESPUBLIKOS PREZIDENTĖ                                                    DALIA GRYBAUSKAITĖ\n\n_________________"
    }
  ],
  "definitions": []
}
