{
  "id": "lt-law-i-1530",
  "type": "statute",
  "title": "Lietuvos Respublikos ir Tarptautinio rekonstrukcijos ir plėtros banko sutarties dėl 10 mln. JAV dolerių paskolos Energijos taupymo (BŪSTO) demonstraciniam projektui finansuoti ratifikavimo įstatymas",
  "short_name": "I-1530",
  "status": "in_force",
  "issued_date": "1996-09-24",
  "in_force_date": "1996-10-04",
  "url": "https://e-tar.lt/portal/lt/legalAct/TAR.67243091B0B4",
  "provisions": [
    {
      "provision_ref": "art1",
      "section": "1",
      "title": "1 straipsnis. Sutarties ratifikavimas",
      "content": "Lietuvos Respublikos Seimas, vadovaudamasis Lietuvos Respublikos Konstitucijos 67 straipsnio 16 punktu ir atsižvelgdamas į Respublikos Prezidento 1996 m. rugsėjo 3 d. dekretą „Dėl teikimo Lietuvos Respublikos Seimui ratifikuoti Lietuvos Respublikos ir Tarptautinio rekonstrukcijos ir plėtros banko sutartį dėl paskolos Energijos taupymo (Būsto) demonstraciniam projektui finansuoti“, ratifikuoja Lietuvos Respublikos ir Tarptautinio rekonstrukcijos ir plėtros banko sutartį dėl 10 mln. JAV dolerių paskolos Energijos taupymo (Būsto) demonstraciniam projektui finansuoti, pasirašytą 1996 m. rugpjūčio 6 d. Vašingtone.\n\nSkelbiu šį Lietuvos Respublikos Seimo priimtą įstatymą.\n\nRESPUBLIKOS PREZIDENTAS                                                       ALGIRDAS BRAZAUSKAS\n______________"
    }
  ],
  "definitions": []
}
