{
  "id": "lt-law-x-534",
  "type": "statute",
  "title": "Lietuvos Respublikos įstatymo \"Dėl Monrealio protokolo dėl medžiagų, ardančių ozono sluoksnį, Londono ir Kopenhagos papildymų bei pataisų ratifikavimo\" 2 straipsnio pripažinimo netekusiu galios įstatymas",
  "short_name": "X-534",
  "status": "in_force",
  "issued_date": "2006-03-30",
  "in_force_date": "2006-04-20",
  "url": "https://e-tar.lt/portal/lt/legalAct/TAR.83E0881F404B",
  "provisions": [
    {
      "provision_ref": "art1",
      "section": "1",
      "title": "1 straipsnis. 2 straipsnio pripažinimas netekusiu galios",
      "content": "2 straipsnį pripažinti netekusiu galios.\n\nSkelbiu šį Lietuvos Respublikos Seimo priimtą įstatymą.\n\nRESPUBLIKOS PREZIDENTAS                                                                  VALDAS ADAMKUS\n______________"
    }
  ],
  "definitions": []
}
