{
  "id": "lt-law-ix-2273",
  "type": "statute",
  "title": "Lietuvos Respublikos užsienio valiutos Lietuvos Respublikoje įstatymo 3 straipsnio papildymo įstatymas",
  "short_name": "IX-2273",
  "status": "in_force",
  "issued_date": "2004-06-15",
  "in_force_date": "2004-06-24",
  "url": "https://e-tar.lt/portal/lt/legalAct/TAR.8C3A323A7089",
  "provisions": [
    {
      "provision_ref": "art1",
      "section": "1",
      "title": "1 straipsnis. 3 straipsnio papildymas 4 dalimi",
      "content": "Papildyti 3 straipsnį 4 dalimi:\n\n„Užsienio valiuta šalių susitarimu taip pat gali būti naudojama mokėjimams ir atsiskaitymams grynaisiais pinigais orlaiviuose ir jūrų laivuose su Lietuvos valstybės vėliava ar skiriamaisiais ženklais, vežančiuose krovinius ir keleivius tarptautiniais maršrutais.“\n\nSkelbiu šį Lietuvos Respublikos Seimo priimtą įstatymą.\n\nLAIKINAI EINANTIS\nRESPUBLIKOS PREZIDENTO PAREIGAS                                      ARTŪRAS PAULAUSKAS\n______________"
    }
  ],
  "definitions": []
}
