{
  "id": "lt-law-viii-1623",
  "type": "statute",
  "title": "Lietuvos Respublikos ir Bulgarijos Respublikos sutarties dėl Lietuvos Respublikos ginkluotųjų pajėgų, dalyvaujančių daugianacionalinėse ginkluotosiose pajėgose \"KFOR\", tranzito per Bulgarijos Respublikos teritoriją sąlygų ir tvarkos ratifikavimo įstatymas",
  "short_name": "VIII-1623",
  "status": "in_force",
  "issued_date": "2000-04-13",
  "in_force_date": "2000-05-19",
  "url": "https://e-tar.lt/portal/lt/legalAct/TAR.AF5F75851CD7",
  "provisions": [
    {
      "provision_ref": "art1",
      "section": "1",
      "title": "1 straipsnis. Sutarties ratifikavimas",
      "content": "Lietuvos Respublikos Seimas, vadovaudamasis Lietuvos Respublikos Konstitucijos 67 straipsnio 16 punktu ir 138 straipsnio 1 dalies 4 punktu bei atsižvelgdamas į Respublikos Prezidento 2000 m. kovo 27 d. dekretą „Dėl teikimo Lietuvos Respublikos Seimui ratifikuoti Lietuvos Respublikos ir Bulgarijos Respublikos sutartį dėl Lietuvos Respublikos ginkluotųjų pajėgų, dalyvaujančių daugianacionalinėse ginkluotosiose pajėgose „KFOR“, tranzito per Bulgarijos Respublikos teritoriją sąlygų ir tvarkos“, ratifikuoja Lietuvos Respublikos ir Bulgarijos Respublikos sutartį dėl Lietuvos Respublikos ginkluotųjų pajėgų, dalyvaujančių daugianacionalinėse ginkluotosiose pajėgose „KFOR“, tranzito per Bulgarijos Respublikos teritoriją sąlygų ir tvarkos, sudarytą apsikeičiant diplomatinėmis notomis 2000 m. vasario 24 d. Varšuvoje.\n\nSkelbiu šį Lietuvos Respublikos Seimo priimtą įstatymą.\n\nRESPUBLIKOS PREZIDENTAS                                                                  VALDAS ADAMKUS\n______________"
    }
  ],
  "definitions": []
}
