{
  "id": "lt-law-xi-1878",
  "type": "statute",
  "title": "Lietuvos Respublikos užsienio valiutos Lietuvos Respublikoje įstatymo 3 straipsnio pakeitimo įstatymas",
  "short_name": "XI-1878",
  "status": "in_force",
  "issued_date": "2011-12-22",
  "in_force_date": "2011-12-31",
  "url": "https://e-tar.lt/portal/lt/legalAct/TAR.B42FBDAB7895",
  "provisions": [
    {
      "provision_ref": "art1",
      "section": "1",
      "title": "1 straipsnis. 3 straipsnio 1 dalies pakeitimas",
      "content": "Pakeisti 3 straipsnio 1 dalį ir ją išdėstyti taip:\n\n„Litus į užsienio valiutą, užsienio valiutą į litus ar vieną užsienio valiutą į kitą užsienio valiutą keičia (perka, parduoda) kredito įstaigos, turinčios tokiai veiklai įstatymų nustatyta tvarka išduotus leidimus (licencijas), elektroninių pinigų įstaigos, kai tai yra susiję su elektroninių pinigų leidimu ir mokėjimo paslaugų teikimu, kiti mokėjimo paslaugų teikėjai, kai tai yra susiję su mokėjimo paslaugų teikimu, ir finansų maklerio įmonės, kai tai yra susiję su investicinių paslaugų teikimu.“\n\nSkelbiu šį Lietuvos Respublikos Seimo priimtą įstatymą.\n\nRESPUBLIKOS PREZIDENTĖ                                                    DALIA GRYBAUSKAITĖ\n\n_________________"
    }
  ],
  "definitions": []
}
