{
  "id": "lt-law-xi-1960",
  "type": "statute",
  "title": "Lietuvos Respublikos Konstitucijos 119 straipsnio pakeitimo įstatymo taikymo tvarkos konstitucinio įstatymo pripažinimo netekusiu galios įstatymas",
  "short_name": "XI-1960",
  "status": "in_force",
  "issued_date": "2012-04-12",
  "in_force_date": "2012-04-24",
  "url": "https://e-tar.lt/portal/lt/legalAct/TAR.BFCFDC408B0B",
  "provisions": [
    {
      "provision_ref": "art1",
      "section": "1",
      "title": "1 straipsnis. Įstatymo pripažinimas netekusiu galios",
      "content": "Lietuvos Respublikos Konstitucijos 119 straipsnio pakeitimo įstatymo taikymo tvarkos konstitucinį įstatymą pripažinti netekusiu galios.\n\nSkelbiu šį Lietuvos Respublikos Seimo priimtą įstatymą.\n\nRESPUBLIKOS PREZIDENTĖ                                                    DALIA GRYBAUSKAITĖ\n\n_________________"
    }
  ],
  "definitions": []
}
