{
  "id": "lt-law-i-2522",
  "type": "statute",
  "title": "Dėl Lietuvos Respublikos žemės ūkio įmonių turto privatizavimo įstatymo papildymo ir pakeitimo",
  "short_name": "I-2522",
  "status": "in_force",
  "issued_date": "1992-04-23",
  "in_force_date": "1992-04-30",
  "url": "https://e-tar.lt/portal/lt/legalAct/TAR.C87205318488",
  "provisions": [
    {
      "provision_ref": "art1",
      "section": "1",
      "title": "LIETUVOS RESPUBLIKOS",
      "content": "LIETUVOS RESPUBLIKOS\nĮ S T A T Y M A S\nDĖL LIETUVOS RESPUBLIKOS ŽEMĖS ŪKIO ĮMONIŲ TURTO PRIVATIZAVIMO ĮSTATYMO PAPILDYMO IR PAKEITIMO\n\n1992 m. balandžio 23 d. Nr. I-2522\nVilnius\n\nLietuvos Respublikos Aukščiausioji Taryba nutaria:\n\nPadaryti Lietuvos Respublikos žemės ūkio įmonių turto privatizavimo įstatyme (Žin., 1991, Nr. 24-637) šiuos papildymus ir pakeitimus:\n\n1. 1 straipsnio 1 punktą išdėstyti taip:\n\n„1. Šis įstatymas reglamentuoja žemės ūkio įmonių turto privatizavimo pirmojo etapo sąlygas ir tvarką.“\n\n2. 3 straipsnio 1 punktą išdėstyti taip:\n\n„1) įmonės darbuotojai, nariai;“\n\n3. 3 straipsnį papildyti 10 punktu:\n\n„10) kiti Lietuvos Respublikos įstatymuose nustatyti asmenys.“\n\n4. 5 straipsnį papildyti 7 punktu:\n\n„7. Šio straipsnio 1 punkto 1–4 papunkčiuose nurodytos lėšos paveldimos bendra tvarka.“\n\nLIETUVOS RESPUBLIKOS AUKŠČIAUSIOSIOS\nTARYBOS PIRMININKO PAVADUOTOJAS                                     KAZIMIERAS MOTIEKA\n______________"
    }
  ],
  "definitions": []
}
