{
  "id": "lt-law-xi-1318",
  "type": "statute",
  "title": "Lietuvos Respublikos sveikatos sistemos įstatymo 40 straipsnio pakeitimo įstatymas",
  "short_name": "XI-1318",
  "status": "in_force",
  "issued_date": "2011-04-14",
  "in_force_date": "2011-04-28",
  "url": "https://e-tar.lt/portal/lt/legalAct/TAR.F8CAD98BC5FC",
  "provisions": [
    {
      "provision_ref": "art1",
      "section": "1",
      "title": "1 straipsnis. 40 straipsnio pakeitimas",
      "content": "Pakeisti 40 straipsnį ir jį išdėstyti taip:\n\n„40 straipsnis. Privalomųjų valstybinių sveikatos programų ir sveikatos stiprinimo programų finansavimas\n\nPrivalomosios valstybinės sveikatos programos, taip pat tradicinių Lietuvos religinių bendruomenių ir bendrijų, asociacijų, labdaros ir paramos fondų, viešųjų įstaigų, kurių steigėjas, dalininkas ar narys nėra valstybės ar savivaldybės institucija ar įstaiga, išskyrus atvejus, kai valstybės ar savivaldybės dalyvavimas grindžiamas nekilnojamojo turto skyrimu panaudos būdu teisės aktų nustatyta tvarka, vykdomos sveikatos stiprinimo programos finansuojamos iš valstybės biudžeto lėšų, kurios numatomos Sveikatos apsaugos ministerijai.“\n\nSkelbiu šį Lietuvos Respublikos Seimo priimtą įstatymą.\n\nRESPUBLIKOS PREZIDENTĖ                                                    DALIA GRYBAUSKAITĖ\n\n_________________"
    }
  ],
  "definitions": []
}
