{
  "document_id": "073b83f0696f11eca9ac839120d251c4",
  "atv_dok_nr": "XIV-823",
  "title": "Lietuvos Respublikos sutelktinio finansavimo įstatymo Nr. XII-2690 pripažinimo netekusiu galios įstatymas",
  "selected_suvestines_id": "zTUipXnIwi",
  "selected_galioja_nuo": "2023-11-10T00:00:00",
  "selected_galioja_iki": null,
  "source_model": "Suvestine",
  "source_url": "https://e-tar.lt/portal/lt/legalAct/073b83f0696f11eca9ac839120d251c4/zTUipXnIwi",
  "raw_text_length": 2811,
  "parsed_provisions": 2,
  "parsed_definitions": 0
}
