{
  "document_id": "0b55f3702f0c11efbdaea558de59136c",
  "atv_dok_nr": "XIV-2750",
  "title": "Lietuvos Respublikos viešųjų pirkimų įstatymo Nr. I-1491 45 straipsnio pakeitimo įstatymas",
  "selected_suvestines_id": "GAJLMJXfsW",
  "selected_galioja_nuo": "2024-06-21T00:00:00",
  "selected_galioja_iki": null,
  "source_model": "Suvestine",
  "source_url": "https://e-tar.lt/portal/lt/legalAct/0b55f3702f0c11efbdaea558de59136c/GAJLMJXfsW",
  "raw_text_length": 2063,
  "parsed_provisions": 1,
  "parsed_definitions": 0
}
