{
  "document_id": "22b9de2012bd11efbcbfb318996800a8",
  "atv_dok_nr": "XIV-2613",
  "title": "Lietuvos Respublikos teismų įstatymo Nr. I-480 44-1, 98, 101 straipsnių pakeitimo ir Įstatymo papildymo 44-3 straipsniu įstatymas",
  "selected_suvestines_id": "JjgbvysuSr",
  "selected_galioja_nuo": "2024-09-01T00:00:00",
  "selected_galioja_iki": null,
  "source_model": "Suvestine",
  "source_url": "https://e-tar.lt/portal/lt/legalAct/22b9de2012bd11efbcbfb318996800a8/JjgbvysuSr",
  "raw_text_length": 4775,
  "parsed_provisions": 5,
  "parsed_definitions": 0
}
