{
  "document_id": "47030120ef3211e4927fda1d051299fb",
  "atv_dok_nr": "XII-1658",
  "title": "Lietuvos Respublikos įstatymas dėl Europos Sąjungos bei jos valstybių narių ir Kolumbijos bei Peru prekybos susitarimo ratifikavimo",
  "selected_suvestines_id": null,
  "selected_galioja_nuo": null,
  "selected_galioja_iki": null,
  "source_model": "Dokumentas",
  "source_url": "https://e-tar.lt/portal/lt/legalAct/47030120ef3211e4927fda1d051299fb",
  "raw_text_length": 1182,
  "parsed_provisions": 2,
  "parsed_definitions": 0
}
