{
  "document_id": "521d71905d8e11e79198ffdb108a3753",
  "atv_dok_nr": "XIII-516",
  "title": "Lietuvos Respublikos laisvųjų ekonominių zonų pagrindų įstatymo Nr. I-976 2, 7, 12, 15 straipsnių pakeitimo ir 16 straipsnio pripažinimo netekusiu galios įstatymas",
  "selected_suvestines_id": "BUsjFPJgCP",
  "selected_galioja_nuo": "2017-07-01T00:00:00",
  "selected_galioja_iki": null,
  "source_model": "Suvestine",
  "source_url": "https://e-tar.lt/portal/lt/legalAct/521d71905d8e11e79198ffdb108a3753/BUsjFPJgCP",
  "raw_text_length": 6012,
  "parsed_provisions": 6,
  "parsed_definitions": 0
}
