{
  "document_id": "68e00f40697411eca9ac839120d251c4",
  "atv_dok_nr": "XIV-837",
  "title": "Lietuvos Respublikos regioninės plėtros įstatymo Nr. VIII-1889 pakeitimo įstatymas",
  "selected_suvestines_id": "uZGAKeGsqh",
  "selected_galioja_nuo": "2022-01-01T00:00:00",
  "selected_galioja_iki": null,
  "source_model": "Suvestine",
  "source_url": "https://e-tar.lt/portal/lt/legalAct/68e00f40697411eca9ac839120d251c4/uZGAKeGsqh",
  "raw_text_length": 76901,
  "parsed_provisions": 32,
  "parsed_definitions": 6
}
