{
  "document_id": "881d39d06eb711ec993ff5ca6e8ba60c",
  "atv_dok_nr": "XIV-879",
  "title": "Lietuvos Respublikos vidaus tarnybos statuto 4, 7, 16, 18, 25, 28, 30, 31, 32 straipsnių ir priedo pakeitimo įstatymas",
  "selected_suvestines_id": "CteEthrAQf",
  "selected_galioja_nuo": "2022-07-01T00:00:00",
  "selected_galioja_iki": null,
  "source_model": "Suvestine",
  "source_url": "https://e-tar.lt/portal/lt/legalAct/881d39d06eb711ec993ff5ca6e8ba60c/CteEthrAQf",
  "raw_text_length": 7744,
  "parsed_provisions": 11,
  "parsed_definitions": 0
}
