{
  "document_id": "a5fba50017b311ec9f09e7df20500045",
  "atv_dok_nr": "XIV-526",
  "title": "Lietuvos Respublikos vidaus vandenų transporto kodekso 2, 3 ir 6 straipsnių pakeitimo įstatymas",
  "selected_suvestines_id": "wLQgQteOrT",
  "selected_galioja_nuo": "2021-09-18T00:00:00",
  "selected_galioja_iki": null,
  "source_model": "Suvestine",
  "source_url": "https://e-tar.lt/portal/lt/legalAct/a5fba50017b311ec9f09e7df20500045/wLQgQteOrT",
  "raw_text_length": 2879,
  "parsed_provisions": 4,
  "parsed_definitions": 2
}
