{
  "document_id": "cef1b410e4c011e7acd7ea182930b17f",
  "atv_dok_nr": "XIII-878",
  "title": "Lietuvos Respublikos prekybinės laivybos įstatymo Nr. I-1513 2, 7, 11, 84, 88, 89 straipsnių ir priedo pakeitimo įstatymas",
  "selected_suvestines_id": "wLlzNypRyG",
  "selected_galioja_nuo": "2018-01-01T00:00:00",
  "selected_galioja_iki": null,
  "source_model": "Suvestine",
  "source_url": "https://e-tar.lt/portal/lt/legalAct/cef1b410e4c011e7acd7ea182930b17f/wLlzNypRyG",
  "raw_text_length": 5431,
  "parsed_provisions": 8,
  "parsed_definitions": 0
}
