{
  "document_id": "TAR.9E71326D9433",
  "atv_dok_nr": "XI-1238",
  "title": "Lietuvos Respublikos išmokų vaikams įstatymo 6, 8, 12, 13, 20 straipsnių pakeitimo ir papildymo ir 22 straipsnio pripažinimo netekusiu galios įstatymo 7 straipsnio pakeitimo įstatymas",
  "selected_suvestines_id": null,
  "selected_galioja_nuo": null,
  "selected_galioja_iki": null,
  "source_model": "Dokumentas",
  "source_url": "https://e-tar.lt/portal/lt/legalAct/TAR.9E71326D9433",
  "raw_text_length": 909,
  "parsed_provisions": 1,
  "parsed_definitions": 0
}
